py_linq/__init__.py
py_linq/core.py
py_linq/decorators.py
py_linq/exceptions.py
py_linq/py_linq.py
py_linq-1.2.5.dist-info/LICENSE
py_linq-1.2.5.dist-info/WHEEL
py_linq-1.2.5.dist-info/METADATA
py_linq-1.2.5.dist-info/RECORD
