Metadata-Version: 2.1
Name: py-linq
Version: 1.2.5
Summary: LINQ (Language Integrated Query) is a popular querying language available in .NET. This library ports the language so that developers can query collections of objects using the same syntax. This library would be useful for Python developers with experience using the expressiveness and power of LINQ.
Home-page: https://github.com/viralogic/py-enumerable
License: MIT
Keywords: LINQ,py-linq
Author: Bruce Fenske
Author-email: bwfenske@ualberta.ca
Requires-Python: >=3.6.1
Classifier: License :: OSI Approved :: MIT License
Classifier: Programming Language :: Python :: 3
Classifier: Programming Language :: Python :: 3.7
Classifier: Programming Language :: Python :: 3.8
Classifier: Programming Language :: Python :: 3.9
Requires-Dist: future (>=0.18.2,<0.19.0)
Project-URL: Repository, https://github.com/viralogic/py-enumerable
